c_temp_api-0.0.1.dist-info/licenses/LICENSE
current_temp_api/__init__.py
current_temp_api/api.py
current_temp_api/base.py
c_temp_api-0.0.1.dist-info/METADATA
c_temp_api-0.0.1.dist-info/WHEEL
c_temp_api-0.0.1.dist-info/top_level.txt
c_temp_api-0.0.1.dist-info/RECORD
