Metadata-Version: 2.4
Name: c_temp_api
Version: 0.0.1
Summary: A client to collect temperature data from various service providers via API
Home-page: https://github.com/miaddehghani/Python-Current-Temp-API
Author: Miad Dehghani
Author-email: miaddehghani1365@gmail.com
Classifier: Programming Language :: Python :: 3
Classifier: License :: OSI Approved :: MIT License
Classifier: Operating System :: OS Independent
Requires-Python: >=3.6
License-File: LICENSE
Requires-Dist: requests
Dynamic: author
Dynamic: author-email
Dynamic: classifier
Dynamic: description
Dynamic: description-content-type
Dynamic: home-page
Dynamic: license-file
Dynamic: requires-dist
Dynamic: requires-python
Dynamic: summary
